gam/__init__.py
gam/clustering.py
gam/gam.py
gam/kendall_tau_distance.py
gam/spearman_distance.py
tests/test_banditPAM.py
tests/test_clustering.py
tests/test_gam.py
tests/test_kendall_tau_distance.py
tests/test_spearman_distance.py
gam-1.3.0.dist-info/LICENSE
gam-1.3.0.dist-info/METADATA
gam-1.3.0.dist-info/WHEEL
gam-1.3.0.dist-info/top_level.txt
gam-1.3.0.dist-info/RECORD
