Metadata-Version: 2.1
Name: gam
Version: 1.3.0
Summary: Global Explanations for Deep Neural Networks
Home-page: https://github.com/capitalone/global-attribution-mapping
Maintainer: Brian Barr
Maintainer-email: brian.barr@capitalone.com
License: Apache License 2.0
Platform: UNKNOWN
Classifier: Programming Language :: Python :: 3
Requires-Python: >=3.6
License-File: LICENSE
Requires-Dist: pandas (>=1.1.3)
Requires-Dist: scikit-learn (>=0.23.2)
Requires-Dist: numpy (>=1.19.2)
Requires-Dist: kaleido (==0.2.1)
Provides-Extra: complete
Requires-Dist: dask[complete] (>=2021.2.0) ; extra == 'complete'
Requires-Dist: dask-distance (>=0.2.0) ; extra == 'complete'
Requires-Dist: dask-ml (>=1.8.0) ; extra == 'complete'
Requires-Dist: plotly-express (>=0.4.1) ; extra == 'complete'
Requires-Dist: nbformat (>=4.2.0) ; extra == 'complete'
